{
    "inicio":
    {
        "usuario_input":"//*[@id='usuario']",
        "senha_input":"//*[@id='senha']",
        "boton_submt":"/html/body/div/form/div/div/div/table/tbody/tr[2]/td/table/tbody/tr[2]/td/table/tbody/tr[7]/td/input"
    },
    "flujo_decretos":{
        "opcion_reporte":"/html/body/div/nav/div/div/ul/li[6]/a",
        "reporte_decretos":"/html/body/div/nav/div/div/ul/li[6]/ul/li[13]/a",
        "estado_reporte":"//*[@id='estado']",
        "fecha_inicio":"//*[@id='FE_REGISTRO_INICIO']",
        "fecha_fin":"//*[@id='FE_REGISTRO_FIN']",
        "estado":"//*[@id='estado']",
        "btn_buscar":"//*[@id='Buscar']",
        "tabla_cabecera":"/html/body/div[1]/form/div/div/div/table/tbody/tr[2]/td/table[3]/thead/tr/th",
        "linea_cantidadReg":"//*[@id='page-wrapper']/div/div/table/tbody/tr[2]/td/table[3]/tbody/tr",
        "select_pagina":"//*[@id='Pagina']",
        "tabla_registro":"/html/body/div[1]/form/div/div/div/table/tbody/tr[2]/td/table[3]/tbody/tr"
    },
    "flujo_salas":{
        "opcion_salas":"/html/body/div/nav/div/div/ul/li[10]/a",
        "opcion_reporte_salas":"/html/body/div/nav/div/div/ul/li[10]/ul/li[1]/a",
        "estado_bandeja":"//*[@id='cbo_est_ban']",
        "numero_sala":"//*[@id='cbo_sala_exp']",
        "fec_vec_ini":"//*[@id='txtFechaFin1']",
        "fec_vec_fin":"//*[@id='txtFechaFin2']",
        "fec_prn_ini":"//*[@id='txtFechaFin3']",
        "fec_prn_fin":"//*[@id='txtFechaFin4']",
        "fec_pro_ini":"//*[@id='txtFechaFin1']",
        "fec_pro_fin":"//*[@id='txtFechaFin2']",
        "fec_acp_ini":"//*[@id='txtFechaFin3']",
        "fec_acp_fin":"//*[@id='txtFechaFin4']",
        "tipo_expediente":"//*[@id='TI_PROCESO']",
        "tipo_remision_sala":"//*[@id='id_cont']",
        "btn_buscar":"//*[@id='Buscar']",
        "tabla_cabecera":"/html/body/div[1]/form/div/div/div/table/tbody/tr[2]/td/table[3]/thead/tr/th",
        "linea_cantidadReg":"/html/body/div[1]/form/div/div/div/table/tbody/tr[2]/td/table[3]/tbody[2]/tr",
        "tabla_registro":"/html/body/div[1]/form/div/div/div/table/tbody/tr[2]/td/table[3]/tbody[1]/tr",
        "select_pagina":"//*[@id='Pagina']"
    }
}
